equia/__init__.py
equia/equia_client.py
equia/options.py
equia/str_util.py
equia/types.py
equia/units.py
equia/demofluids/__init__.py
equia/demofluids/demofluid1_nHexane_Ethylene_HDPE7.py
equia/demofluids/demofluid_Methane_nHexane_Toluene.py
equia/models/__init__.py
equia/models/api_fluid.py
equia/models/api_fluid_component_block.py
equia/models/api_fluid_distribution_moment.py
equia/models/api_fluid_kij.py
equia/models/api_fluid_polymer_component.py
equia/models/api_fluid_pseudo_component.py
equia/models/api_fluid_standard_component.py
equia/models/api_output_calculation_result_phase.py
equia/models/api_output_calculation_result_phase_composition.py
equia/models/api_output_calculation_result_phase_polymer_moment.py
equia/models/api_output_calculation_result_phase_polymer_moments.py
equia/models/api_output_calculation_result_point.py
equia/models/api_output_eospropertiestpn_ideal.py
equia/models/api_output_eospropertiestpn_residual.py
equia/models/api_output_eospropertiestpn_result.py
equia/models/api_output_eospropertiestpn_sum.py
equia/models/api_output_phasediagram.py
equia/models/api_output_phasediagram_point.py
equia/models/api_profile_information.py
equia/models/api_profile_time_information.py
equia/models/api_value_component_composition.py
equia/models/api_value_compressibility.py
equia/models/api_value_density.py
equia/models/api_value_enthalpy.py
equia/models/api_value_entropy.py
equia/models/api_value_floating_with_out_units.py
equia/models/api_value_floating_with_out_units_name.py
equia/models/api_value_floating_with_units.py
equia/models/api_value_mole_percent.py
equia/models/api_value_pressure.py
equia/models/api_value_temperature.py
equia/models/api_value_volume.py
equia/models/api_value_weight_percent.py
equia/models/batchflash_calculation_result.py
equia/models/batchflash_fixed_temperature_pressure_calculation_input.py
equia/models/batchflash_fixed_temperature_pressure_calculation_item.py
equia/models/calculation_composition.py
equia-0.1.9.dist-info/licenses/LICENSE
equia-0.1.9.dist-info/METADATA
equia-0.1.9.dist-info/WHEEL
equia-0.1.9.dist-info/top_level.txt
equia-0.1.9.dist-info/RECORD
