Metadata-Version: 2.4
Name: Equia
Version: 0.1.9
Summary: Python SDK for accessing Equia API
Home-page: https://github.com/vlxe/equia-python-sdk
Author: "VLXE A/S"
Author-email: VLXE A/S <tl@vlxe.com>
Project-URL: Homepage, https://github.com/vlxe/equia.python.sdk
Project-URL: Bug Tracker, https://github.com/vlxe/equia.python.sdk/issues
Classifier: Programming Language :: Python :: 3
Classifier: License :: OSI Approved :: MIT License
Classifier: Operating System :: OS Independent
Requires-Python: >=3.7
License-File: LICENSE
Dynamic: license-file
